<?xml version="1.0" encoding="UTF-8"?>
<objects serializationModel="Studio.02.00.00">
	<object class="AudioFile" id="{ca7da0e0-fb12-4384-8e63-c6157865c60c}">
		<property name="assetPath">
			<value>PotionDrink_Liquid_06.wav</value>
		</property>
		<property name="frequencyInKHz">
			<value>44.0999985</value>
		</property>
		<property name="channelCount">
			<value>1</value>
		</property>
		<property name="length">
			<value>0.46934240362811791</value>
		</property>
		<relationship name="masterAssetFolder">
			<destination>{b734c849-b682-419f-8c74-545e527a41bd}</destination>
		</relationship>
	</object>
</objects>
