<?xml version="1.0" encoding="UTF-8"?>
<objects serializationModel="Studio.02.00.00">
	<object class="AudioFile" id="{e95786f0-e38c-4385-bd99-41aa07499471}">
		<property name="assetPath">
			<value>Element_SetDown_04.wav</value>
		</property>
		<property name="frequencyInKHz">
			<value>44.0999985</value>
		</property>
		<property name="channelCount">
			<value>1</value>
		</property>
		<property name="length">
			<value>0.30768707482993196</value>
		</property>
		<relationship name="masterAssetFolder">
			<destination>{b734c849-b682-419f-8c74-545e527a41bd}</destination>
		</relationship>
	</object>
</objects>
